[{"nome":"Teatro dos Grandes Atores","latitude":"-23.000442","longitude":"-43.349943","endereco":"Avenida das Américas,  3555 - Barra da Tijuca"},{"nome":"Centro Cultural Anglo Americano (Suassuna)","latitude":"-23.000965","longitude":"-43.334382","endereco":"Avenida das Américas, 2603 - Barra da Tijuca"},{"nome":"Campo de Santana","latitude":"-22.906667","longitude":"-43.188333","endereco":"Avenida Presidente Vargas, s/n - Centro"},{"nome":"Sambódromo","latitude":"-22.911470","longitude":"-43.196838","endereco":"Rua Marquês de Sapucaí, s/n - Santo Cristo"},{"nome":"Teatro Ziembinski","latitude":"-22.920947","longitude":"-43.223917","endereco":"Avenida Heitor Beltrão, s/n - Tijuca"},{"nome":"Teatro CEC Antonio Fagundes","latitude":"-22.990025","longitude":"-43.366205","endereco":"Avenida Ayrton Senna, 2541A - Barra da Tijuca"},{"nome":"Cidade das Artes","latitude":"-22.998611","longitude":"-43.365556","endereco":"Avenida das Américas, s/n - Barra da Tijuca"},{"nome":"Parque Nacional da Tijuca","latitude":"-22.959831","longitude":"-43.278288","endereco":"Estrada da Cascatinha, 850 - Alto da Boa Vista"},{"nome":"Casa França Brasil","latitude":"-22.900394","longitude":"-43.175986","endereco":"Rua Visconde de Itaboraí, 78 - Centro"},{"nome":"Centro Cultural Banco do Brasil","latitude":"-22.900606","longitude":"-43.176517","endereco":"Rua Primeiro de Março, 66 - Centro"},{"nome":"Centro Cultural dos Correios","latitude":"-22.901291","longitude":"-43.175839","endereco":"Rua Visconde de Itaboraí, 20 - Centro"},{"nome":"Confeitaria Colombo","latitude":"-22.905249","longitude":"-43.178803","endereco":"Rua Gonçalves Dias, 32 - Centro"},{"nome":"Igreja Nossa Senhora da Candelária","latitude":"-22.900735","longitude":"-43.177643","endereco":"Praça Pio X, s/n - Centro"},{"nome":"Real Gabinete Português de Leitura","latitude":"-22.905466","longitude":"-43.182171","endereco":"Rua Luís de Camões, 30 - Centro"},{"nome":"Teatro João Caetano","latitude":"-22.906390","longitude":"-43.182289","endereco":"Praça Tiradentes, s/n - Centro"},{"nome":"Mosteiro de São Bento","latitude":"-22.896747","longitude":"-43.177885","endereco":"Rua Dom Gerardo, 68 - Centro"}]