[{"nome":"Santa Teresa","latitude":"-22.931944","longitude":"-43.198056","endereco":"Santa Teresa, s/n - Santa Teresa"},{"nome":"Oi Futuro","latitude":"-22.930000","longitude":"-43.176389","endereco":"Rua Dois de Dezembro, 63 - Flamengo"},{"nome":"Parque Eduardo Guinle","latitude":"-22.931401","longitude":"-43.182485","endereco":"Rua Gago Coutinho, 66 - Laranjeiras"},{"nome":"Cristo Redentor (Corcovado)","latitude":"-22.940436","longitude":"-43.198484","endereco":"Rua Cosme Velho, 513 - Cosme Velho"}]